mod3rd/__init__.py
mod3rd/admin_esp/__app__.py
mod3rd/admin_esp/__init__.py
mod3rd/admin_esp/softap.py
mod3rd/admin_esp/wlan.py
mod3rd/admin_user/__app__.py
mod3rd/admin_user/__init__.py
mod3rd/admin_user/login.py
mod3rd/admin_user/pass_change.py
mod3rd/admin_windup/__app__.py
mod3rd/admin_windup/__init__.py
mod3rd/admin_windup/content.py
mod3rd/admin_windup/editor.py
mod3rd/admin_windup/file_api.py
mod3rd/admin_windup/secsys.py
mod3rd/admin_windup/www_editor/index.html
mod3rd/main_dashboard/__app__.py
mod3rd/main_dashboard/__init__.py
mod3rd/main_dashboard/www_main/index.html
mod3rd/simplicity/__init__.py
mod3rd/simplicity/conv.py
mod3rd/simplicity/core.py
mod3rd/skeleton/__app__.py
mod3rd/skeleton/__init__.py
mod3rd/tempr/__init__.py
mod3rd/tempr/temprec.py
mod3rd/tempr_api/__app__.py
mod3rd/tempr_api/__init__.py
mod3rd/terminal/__app__.py
mod3rd/terminal/__init__.py
mod3rd/terminal/term.py
modcore/__init__.py
modcore/cntrl.py
modcore/events.py
modcore/lic.py
modcore/lifecycle.py
modcore/log.py
modcore/mod.py
modcore/util.py
moddev/__init__.py
moddev/alarmclock.py
moddev/alarmcounter.py
moddev/button.py
moddev/control.py
moddev/eventemitter.py
moddev/interval.py
moddev/iopin.py
moddev/network.py
moddev/ntp.py
moddev/ntp_tz.py
moddev/ntp_tz_cet.py
moddev/sdcard.py
moddev/softap.py
moddev/timeout.py
moddev/webrepl.py
moddev/wlan.py
modext/__init__.py
modext/config/__init__.py
modext/config/config.py
modext/config/namespace.py
modext/config/reprdict.py
modext/fiber/__init__.py
modext/fiber/core.py
modext/fiber/fiber_worker.py
modext/fiber/timer.py
modext/fiber_stream/__init__.py
modext/fiber_stream/channel.py
modext/fiber_stream/stream.py
modext/fiber_stream/stream_util.py
modext/http/__init__.py
modext/http/http_func.py
modext/http/webserv.py
modext/iotk/__init__.py
modext/iotk/iolang.py
modext/irq/__init__.py
modext/irq/intr.py
modext/irq/misc.py.py
modext/misc/__init__.py
modext/misc/async_mod.py
modext/misc/boot.py
modext/misc/main.py
modext/misc/main_async.py
mpymodcore-0.0.24.dist-info/LICENSE
mpymodcore-0.0.24.dist-info/METADATA
mpymodcore-0.0.24.dist-info/WHEEL
mpymodcore-0.0.24.dist-info/top_level.txt
mpymodcore-0.0.24.dist-info/RECORD
